<?xml version="1.0" encoding="UTF-8"?>
<claim>
  <agent_instructed>no</agent_instructed>
  <arrest_warrant_date>2024-01-03</arrest_warrant_date>
  <assigned_counsel>no</assigned_counsel>
  <claim_type>non_standard_magistrate</claim_type>
  <concluded>yes</concluded>
  <conclusion>Case concluded due to guilty plea</conclusion>
  <court>Liverpool Magistrates Court</court>
  <created_at>2024-02-07T10:00:00Z</created_at>
  <defence_statement>15</defence_statement>
  <defendants>
    <defendant>
      <first_name>John</first_name>
      <last_name>Smith</last_name>
      <maat>12345678</maat>
      <position>1</position>
    </defendant>
    <defendant>
      <first_name>Jane</first_name>
      <last_name>Doe</last_name>
      <maat>87654321</maat>
      <position>2</position>
    </defendant>
  </defendants>
  <disbursements>
    <disbursement>
      <disbursement_date>2024-01-15</disbursement_date>
      <disbursement_type>car</disbursement_type>
      <miles>45.5</miles>
      <total_cost_without_vat>20.47</total_cost_without_vat>
      <details>Travel to Liverpool Magistrates Court</details>
      <prior_authority>no</prior_authority>
      <apply_vat>true</apply_vat>
      <vat_amount>4.09</vat_amount>
      <position>1</position>
    </disbursement>
    <disbursement>
      <disbursement_date>2024-01-20</disbursement_date>
      <disbursement_type>other</disbursement_type>
      <other_type>psychiatric_reports</other_type>
      <total_cost_without_vat>350.00</total_cost_without_vat>
      <details>Expert psychiatric assessment</details>
      <prior_authority>yes</prior_authority>
      <apply_vat>true</apply_vat>
      <vat_amount>70.00</vat_amount>
      <position>2</position>
    </disbursement>
  </disbursements>
  <firm_office>
    <account_number>1A234B</account_number>
    <address_line_1>123 Law Street</address_line_1>
    <address_line_2>Suite 100</address_line_2>
    <name>Legal Eagles LLP</name>
    <postcode>L1 2CD</postcode>
    <town>Liverpool</town>
    <vat_registered>yes</vat_registered>
  </firm_office>
  <first_hearing_date>2024-01-10</first_hearing_date>
  <gender>m</gender>
  <has_disbursements>yes</has_disbursements>
  <hearing_outcome>CP03</hearing_outcome>
  <is_other_info>no</is_other_info>
  <main_offence>Assault occasioning actual bodily harm</main_offence>
  <main_offence_date>2023-12-25</main_offence_date>
  <matter_type>1</matter_type>
  <number_of_hearing>3</number_of_hearing>
  <number_of_witnesses>4</number_of_witnesses>
  <office_code>1A234B</office_code>
  <preparation_time>yes</preparation_time>
  <prosecution_evidence>45</prosecution_evidence>
  <plea>guilty</plea>
  <plea_category>category_1a</plea_category>
  <reasons_for_claim>
    <reason>enhanced_rates_claimed</reason>
    <reason>core_costs_exceed_higher_limit</reason>
  </reasons_for_claim>
  <rep_order_date>2023-12-26</rep_order_date>
  <stage_reached>prog</stage_reached>
  <ufn>ABC123/001</ufn>
  <work_items>
    <work_item>
      <completed_on>2024-01-15</completed_on>
      <fee_earner>JS</fee_earner>
      <position>1</position>
      <time_spent>120</time_spent>
      <uplift>20</uplift>
      <work_type>preparation</work_type>
    </work_item>
    <work_item>
      <completed_on>2024-01-16</completed_on>
      <fee_earner>JS</fee_earner>
      <position>2</position>
      <time_spent>60</time_spent>
      <work_type>attendance_without_counsel</work_type>
    </work_item>
    <work_item>
      <completed_on>2024-01-20</completed_on>
      <fee_earner>JS</fee_earner>
      <position>3</position>
      <time_spent>90</time_spent>
      <work_type>travel</work_type>
    </work_item>
  </work_items>
  <youth_court>no</youth_court>
</claim>
