<?xml version="1.0" encoding="UTF-8"?>
<claim>
  <agent_instructed>no</agent_instructed>
  <arrest_warrant_date>2024-01-03</arrest_warrant_date>
  <assigned_counsel>no</assigned_counsel>
  <calls>10</calls>
  <claim_type>non_standard_magistrate</claim_type>
  <concluded>yes</concluded>
  <conclusion>Case concluded due to guilty plea</conclusion>
  <court>Liverpool Magistrates Court</court>
  <court_in_undesignated_area>yes</court_in_undesignated_area>
  <created_at>2024-02-07T10:00:00Z</created_at>
  <defence_statement>15</defence_statement>
  <defendants>
    <defendant>
      <first_name>John</first_name>
      <last_name>Smith</last_name>
      <maat>1234567</maat>
      <main>true</main>
      <position>1</position>
    </defendant>
    <defendant>
      <first_name>Jane</first_name>
      <last_name></last_name>
      <maat>7654321</maat>
      <main>false</main>
      <position>2</position>
    </defendant>
    <defendant>
      <first_name></first_name>
      <last_name>Smith</last_name>
      <maat>7654321</maat>
      <main>false</main>
      <position>3</position>
    </defendant>
  </defendants>
  <disbursements>
    <disbursement>
      <disbursement_date>2024-01-15</disbursement_date>
      <disbursement_type>car</disbursement_type>
      <miles>45.5</miles>
      <total_cost_without_vat>20.47</total_cost_without_vat>
      <details></details>
      <prior_authority>no</prior_authority>
      <apply_vat>true</apply_vat>
      <vat_amount>4.09</vat_amount>
    </disbursement>
    <disbursement>
      <disbursement_date>2024-01-20</disbursement_date>
      <disbursement_type>other</disbursement_type>
      <other_type>psychiatric_reports</other_type>
      <total_cost_without_vat>350.00</total_cost_without_vat>
      <details>Expert psychiatric assessment</details>
      <prior_authority>yes</prior_authority>
      <apply_vat>true</apply_vat>
      <vat_amount>70.00</vat_amount>
    </disbursement>
    <disbursement>
      <disbursement_date>2024-01-21</disbursement_date>
      <disbursement_type>other</disbursement_type>
      <other_type>psychiatric_reports</other_type>
      <total_cost_without_vat>23.45</total_cost_without_vat>
      <details></details>
      <prior_authority>yes</prior_authority>
      <apply_vat>true</apply_vat>
      <vat_amount>70.00</vat_amount>
    </disbursement>
  </disbursements>
  <firm_office>
    <address_line_1>123 Law Street</address_line_1>
    <address_line_2>Suite 100</address_line_2>
    <name>Legal Eagles LLP</name>
    <postcode>FK9 4LA</postcode>
    <town>Liverpool</town>
    <vat_registered>yes</vat_registered>
  </firm_office>
  <first_hearing_date>2024-01-10</first_hearing_date>
  <gender>m</gender>
  <has_disbursements>yes</has_disbursements>
  <hearing_outcome>CP03</hearing_outcome>
  <is_other_info>yes</is_other_info>
  <letters>10</letters>
  <letters_uplift>5</letters_uplift>
  <main_offence>Assault occasioning actual bodily harm</main_offence>
  <main_offence_date>2023-12-25</main_offence_date>
  <main_offence_type>summary_only</main_offence_type>
  <matter_type>1</matter_type>
  <number_of_hearing>3</number_of_hearing>
  <number_of_witnesses>4</number_of_witnesses>
  <office_code>1A123B</office_code>
  <office_in_undesignated_area>yes</office_in_undesignated_area>
  <other_info>Other info</other_info>
  <preparation_time>yes</preparation_time>
  <prosecution_evidence>45</prosecution_evidence>
  <plea>guilty</plea>
  <plea_category>category_1a</plea_category>
  <reason_for_claim_other_details>test</reason_for_claim_other_details>
  <reasons_for_claim>
    <reason>core_costs_exceed_higher_limit</reason>
    <reason>other</reason>
    <reason>representation_order_withdrawn</reason>
  </reasons_for_claim>
  <representation_order_withdrawn_date>2023-12-25</representation_order_withdrawn_date>
  <remitted_to_magistrate>yes</remitted_to_magistrate>
  <remitted_to_magistrate_date>2023-12-25</remitted_to_magistrate_date>
  <rep_order_date>2023-12-26</rep_order_date>
  <solicitor>
    <first_name>Mickey</first_name>
    <last_name>Dolenz</last_name>
    <reference_number>1234456</reference_number>
    <contact_first_name>Davy</contact_first_name>
    <contact_last_name>Jones</contact_last_name>
    <contact_email>davy@jones.com</contact_email>
  </solicitor>
  <supplemental_claim>yes</supplemental_claim>
  <time_spent>210</time_spent>
  <ufn>121212/001</ufn>
  <unassigned_counsel>no</unassigned_counsel>
  <wasted_costs>no</wasted_costs>
  <work_after>yes</work_after>
  <work_after_date>2023-12-26</work_after_date>
  <work_before>yes</work_before>
  <work_before_date>2023-12-26</work_before_date>
  <work_completed_date>2023-12-26</work_completed_date>
  <work_items>
    <work_item>
      <completed_on>2024-01-15</completed_on>
      <fee_earner></fee_earner>
      <time_spent>120</time_spent>
      <uplift>20</uplift>
      <work_type>preparation</work_type>
    </work_item>
    <work_item>
      <completed_on>2024-01-16</completed_on>
      <fee_earner>JS</fee_earner>
      <time_spent>60</time_spent>
      <work_type>attendance_without_counsel</work_type>
    </work_item>
    <work_item>
      <completed_on>2024-01-20</completed_on>
      <fee_earner></fee_earner>
      <time_spent>90</time_spent>
      <work_type>travel</work_type>
    </work_item>
  </work_items>
  <youth_court>no</youth_court>
</claim>
